chill/__init__.py
chill/plugin.py
poetry_chill-0.0.4.dist-info/LICENSE
poetry_chill-0.0.4.dist-info/METADATA
poetry_chill-0.0.4.dist-info/WHEEL
poetry_chill-0.0.4.dist-info/entry_points.txt
poetry_chill-0.0.4.dist-info/RECORD
