Metadata-Version: 2.1
Name: poetry-chill
Version: 0.0.4
Summary: 
Author: Yakov-Varnaev
Author-email: yakov.varnaev@gmail.com
Requires-Python: >=3.10,<4.0
Classifier: Programming Language :: Python :: 3
Classifier: Programming Language :: Python :: 3.10
Classifier: Programming Language :: Python :: 3.11
Classifier: Programming Language :: Python :: 3.12
Requires-Dist: pip_chill (>=1.0.3,<2.0.0)
Requires-Dist: poetry (>=1.8,<2.0)
Requires-Dist: setuptools (>=74.1.1,<75.0.0)
